bookery/__init__.py
bookery/__main__.py
bookery/common/__init__.py
bookery/common/overrides.py
bookery/models/__init__.py
bookery/models/book_model.py
bookery/models/mapped_class_model.py
bookery/models/member_model.py
bookery/persistence/__init__.py
bookery/persistence/base.py
bookery/persistence/book.py
bookery/persistence/member.py
bookery/persistence/view.py
bookery/widgets/__init__.py
bookery/widgets/book_details_page.py
bookery/widgets/books_page.py
bookery/widgets/content_widget.py
bookery/widgets/main_window.py
bookery/widgets/member_details_page.py
bookery/widgets/members_page.py
bookery/widgets/sidebar.py
bookery-0.2.0.dist-info/LICENSE
bookery-0.2.0.dist-info/WHEEL
bookery-0.2.0.dist-info/METADATA
bookery-0.2.0.dist-info/RECORD
