Metadata-Version: 2.1
Name: bookery
Version: 0.2.0
Summary: 
Author: Donghyeon Kim
Author-email: 0916dhkim@gmail.com
Requires-Python: >=3.7,<4.0
Classifier: Programming Language :: Python :: 3
Classifier: Programming Language :: Python :: 3.7
Requires-Dist: PySide2 (>=5.13,<6.0)
Requires-Dist: SQLAlchemy (>=1.3,<2.0)
